{
  "main": {
    "id": "de921bc75658fce4",
    "type": "split",
    "children": [
      {
        "id": "119e2e7036921f37",
        "type": "tabs",
        "children": [
          {
            "id": "bf66b65e6936bd83",
            "type": "leaf",
            "state": {
              "type": "markdown",
              "state": {
                "file": "计算机专业选择.md",
                "mode": "source",
                "source": false
              }
            }
          }
        ]
      }
    ],
    "direction": "vertical"
  },
  "left": {
    "id": "93796aa491ffa235",
    "type": "split",
    "children": [
      {
        "id": "377d0f5f5edbc11a",
        "type": "tabs",
        "children": [
          {
            "id": "0f33619406c0253d",
            "type": "leaf",
            "state": {
              "type": "file-explorer",
              "state": {
                "sortOrder": "alphabetical"
              }
            }
          },
          {
            "id": "95add9b726738d52",
            "type": "leaf",
            "state": {
              "type": "search",
              "state": {
                "query": "",
                "matchingCase": false,
                "explainSearch": false,
                "collapseAll": false,
                "extraContext": false,
                "sortOrder": "alphabetical"
              }
            }
          },
          {
            "id": "3c0ff69250f83b08",
            "type": "leaf",
            "state": {
              "type": "starred",
              "state": {}
            }
          }
        ]
      }
    ],
    "direction": "horizontal",
    "width": 300
  },
  "right": {
    "id": "2dd8a57415198e43",
    "type": "split",
    "children": [
      {
        "id": "001e49ed19e109ef",
        "type": "tabs",
        "children": [
          {
            "id": "f8ba135f916ffc5d",
            "type": "leaf",
            "state": {
              "type": "backlink",
              "state": {
                "file": "计算机专业选择.md",
                "collapseAll": false,
                "extraContext": false,
                "sortOrder": "alphabetical",
                "showSearch": false,
                "searchQuery": "",
                "backlinkCollapsed": false,
                "unlinkedCollapsed": true
              }
            }
          },
          {
            "id": "42e2b587c90581be",
            "type": "leaf",
            "state": {
              "type": "outgoing-link",
              "state": {
                "file": "计算机专业选择.md",
                "linksCollapsed": false,
                "unlinkedCollapsed": true
              }
            }
          },
          {
            "id": "6463612b737c5122",
            "type": "leaf",
            "state": {
              "type": "tag",
              "state": {
                "sortOrder": "frequency",
                "useHierarchy": true
              }
            }
          },
          {
            "id": "bff5b1989f7af04e",
            "type": "leaf",
            "state": {
              "type": "outline",
              "state": {
                "file": "计算机专业选择.md"
              }
            }
          }
        ]
      }
    ],
    "direction": "horizontal",
    "width": 300,
    "collapsed": true
  },
  "active": "bf66b65e6936bd83",
  "lastOpenFiles": []
}